README.md
setup.py
irct_api/__init__.py
irct_api/search.py
irct_api.egg-info/PKG-INFO
irct_api.egg-info/SOURCES.txt
irct_api.egg-info/dependency_links.txt
irct_api.egg-info/requires.txt
irct_api.egg-info/top_level.txt